odoo/addons/stock_inventory_line_open/README.rst
odoo/addons/stock_inventory_line_open/__init__.py
odoo/addons/stock_inventory_line_open/__manifest__.py
odoo/addons/stock_inventory_line_open/i18n/fr.po
odoo/addons/stock_inventory_line_open/i18n/it.po
odoo/addons/stock_inventory_line_open/i18n/stock_inventory_line_open.pot
odoo/addons/stock_inventory_line_open/models/__init__.py
odoo/addons/stock_inventory_line_open/models/stock_inventory.py
odoo/addons/stock_inventory_line_open/readme/CONTRIBUTORS.rst
odoo/addons/stock_inventory_line_open/readme/DESCRIPTION.rst
odoo/addons/stock_inventory_line_open/static/description/icon.png
odoo/addons/stock_inventory_line_open/static/description/index.html
odoo/addons/stock_inventory_line_open/views/stock_inventory_view.xml
odoo14_addon_stock_inventory_line_open-14.0.1.0.1.dev7.dist-info/METADATA
odoo14_addon_stock_inventory_line_open-14.0.1.0.1.dev7.dist-info/WHEEL
odoo14_addon_stock_inventory_line_open-14.0.1.0.1.dev7.dist-info/top_level.txt
odoo14_addon_stock_inventory_line_open-14.0.1.0.1.dev7.dist-info/RECORD
